{"adult": false, "backdrop_path": "/brgYZB9cAuwTfZoHb8nq9FLtWMG.jpg", "belongs_to_collection": null, "budget": 0, "genres": [{"id": 18, "name": "Drama"}], "homepage": "", "id": 1614061, "imdb_id": "tt39305430", "origin_country": ["PH"], "original_language": "tl", "original_title": "Bagong Tukso", "overview": "Meet the freshest faces of VMX! Apphle Celso, Margaret Diaz, Heart Fox, and Allison Ross turn up the heat, bare fantasies, and tease you into an unforgettable sexy experience.", "popularity": 8.6281, "poster_path": "/t7nlhiZNaGdXPmbsTM872VlZgXD.jpg", "production_companies": [{"id": 149142, "logo_path": "/25oYoXHsfWYlddAzJSBReajN3BM.png", "name": "Vivamax", "origin_country": "PH"}], "production_countries": [{"iso_3166_1": "PH", "name": "Philippines"}], "release_date": "2026-01-27", "revenue": 0, "runtime": 70, "spoken_languages": [{"english_name": "Tagalog", "iso_639_1": "tl", "name": ""}], "status": "Released", "tagline": "", "title": "Bagong Tukso", "video": false, "vote_average": 0.0, "vote_count": 0}