{"adult": false, "backdrop_path": "/e3t6v02TbBQxy6F0onYeufnqQz1.jpg", "belongs_to_collection": null, "budget": 0, "genres": [{"id": 18, "name": "Drama"}, {"id": 53, "name": "Thriller"}, {"id": 10749, "name": "Romance"}], "homepage": "", "id": 115221, "imdb_id": "tt0083124", "origin_country": ["JP"], "original_language": "ja", "original_title": "駅 STATION", "overview": "A detective goes out of his way to crack the case of a serial killer who specialises in murdering police officers.", "popularity": 6.9042, "poster_path": "/ASuWq3kDQRdXLe5B5WVXJq0lls.jpg", "production_companies": [{"id": 49301, "logo_path": "/vmLo0piReB0EI1boTiBZ8eDJ7vD.png", "name": "Toho Pictures", "origin_country": "JP"}], "production_countries": [{"iso_3166_1": "JP", "name": "Japan"}], "release_date": "1981-11-07", "revenue": 0, "runtime": 132, "spoken_languages": [{"english_name": "Japanese", "iso_639_1": "ja", "name": "日本語"}], "status": "Released", "tagline": "", "title": "Station", "video": false, "vote_average": 6.1, "vote_count": 12}