{"adult": false, "backdrop_path": "/woAG66LiyVHaueMVLBkNbYSgJ4c.jpg", "belongs_to_collection": null, "budget": 0, "genres": [{"id": 53, "name": "Thriller"}, {"id": 9648, "name": "Mystery"}], "homepage": "https://epic-pictures.com/film/the-huntsman", "id": 1288246, "imdb_id": "tt21087510", "origin_country": ["US"], "original_language": "en", "original_title": "The Huntsman", "overview": "When an ICU nurse volunteers to help a coma patient accused of murdering six women, he’s drawn into a chilling web of lies, obsession, and deadly secrets as a detective races to stop the killer.", "popularity": 10.2152, "poster_path": "/la1CvCbIaXj9Xd9BOSgEBM15uO0.jpg", "production_companies": [], "production_countries": [], "release_date": "2026-02-06", "revenue": 0, "runtime": 103, "spoken_languages": [{"english_name": "English", "iso_639_1": "en", "name": "English"}], "status": "Released", "tagline": "", "title": "The Huntsman", "video": true, "vote_average": 8.0, "vote_count": 3}